<?xml version="1.0" encoding="UTF-8"?>
<objects serializationModel="Studio.02.00.00">
	<object class="AudioFile" id="{b4da6e2f-5b46-4cc2-ab68-8d198ee330a9}">
		<property name="assetPath">
			<value>sfx/portal/Portal_loop_adjacent_to_portal.wav</value>
		</property>
		<property name="isStreaming">
			<value>true</value>
		</property>
		<property name="frequencyInKHz">
			<value>44.0999985</value>
		</property>
		<property name="channelCount">
			<value>1</value>
		</property>
		<property name="length">
			<value>30.549365079365078</value>
		</property>
		<relationship name="masterAssetFolder">
			<destination>{53a945c1-e248-46c5-827e-36403b992cb5}</destination>
		</relationship>
	</object>
</objects>
